{
    "public/wutime_accblock.less": {
        "version_id": 1010070,
        "version_string": "1.1.0",
        "hash": "8f5cab75f7d9e03ad67cb834f344b8b6"
    },
    "public/wutime_accblock_blocks.html": {
        "version_id": 1010070,
        "version_string": "1.1.0",
        "hash": "2717757354873f5973b1eb933198e483"
    },
    "public/wutime_accblock_option_code.html": {
        "version_id": 101,
        "version_string": "0.0.1 1",
        "hash": "61800813219761025ef6a62f364d5c17"
    }
}